tquant/__init__.py
tquant/_tqapi.cp36-win_amd64.pyd
tquant/stralet.py
tquant/test.py
tquant/test2.py
tquant/test_stralet.py
tquant/tqapi.py
tquant-0.1.16.dist-info/METADATA
tquant-0.1.16.dist-info/RECORD
tquant-0.1.16.dist-info/WHEEL
tquant-0.1.16.dist-info/top_level.txt
