Metadata-Version: 2.1
Name: tquant
Version: 0.1.16
Summary: Acqusta quantitative trading tools
Home-page: https://github.com/acqusta/tqapi
Author: Xu Tiezhu
Author-email: xutiezhu@gmail.com
License: UNKNOWN
Platform: UNKNOWN
